README.md
setup.cfg
setup.py
macrobase_driver/__init__.py
macrobase_driver/context.py
macrobase_driver/driver.py
macrobase_driver/endpoint.py
macrobase_driver/exceptions.py
macrobase_driver/hook.py
macrobase_driver/logging.py
macrobase_driver.egg-info/PKG-INFO
macrobase_driver.egg-info/SOURCES.txt
macrobase_driver.egg-info/dependency_links.txt
macrobase_driver.egg-info/requires.txt
macrobase_driver.egg-info/top_level.txt
macrobase_driver/config/__init__.py
macrobase_driver/config/base.py
macrobase_driver/config/configs.py
macrobase_driver/config/fields.py