Metadata-Version: 1.0
Name: macrobase-driver
Version: 2.0.1
Summary: Macrobase drivers base
Home-page: https://github.com/mbcores/macrobase-driver
Author: Alexey Shagaleev
Author-email: alexey.shagaleev@yandex.ru
License: MIT
Platform: UNKNOWN
